pyTooling/py.typed
pyTooling/Attributes/__init__.py
pyTooling/Attributes/ArgParse/Argument.py
pyTooling/Attributes/ArgParse/BooleanFlag.py
pyTooling/Attributes/ArgParse/Flag.py
pyTooling/Attributes/ArgParse/KeyValueFlag.py
pyTooling/Attributes/ArgParse/OptionalValuedFlag.py
pyTooling/Attributes/ArgParse/ValuedFlag.py
pyTooling/Attributes/ArgParse/__init__.py
pyTooling/CLIAbstraction/Argument.py
pyTooling/CLIAbstraction/BooleanFlag.py
pyTooling/CLIAbstraction/Command.py
pyTooling/CLIAbstraction/Flag.py
pyTooling/CLIAbstraction/KeyValueFlag.py
pyTooling/CLIAbstraction/OptionalValuedFlag.py
pyTooling/CLIAbstraction/ValuedFlag.py
pyTooling/CLIAbstraction/ValuedFlagList.py
pyTooling/CLIAbstraction/ValuedTupleFlag.py
pyTooling/CLIAbstraction/__init__.py
pyTooling/CallByRef/__init__.py
pyTooling/Cartesian2D/Shapes.py
pyTooling/Cartesian2D/__init__.py
pyTooling/Cartesian3D/Volumes.py
pyTooling/Cartesian3D/__init__.py
pyTooling/Common/__init__.py
pyTooling/Configuration/JSON.py
pyTooling/Configuration/YAML.py
pyTooling/Configuration/__init__.py
pyTooling/Decorators/__init__.py
pyTooling/Dependency/Python.py
pyTooling/Dependency/__init__.py
pyTooling/Exceptions/__init__.py
pyTooling/Filesystem/__init__.py
pyTooling/GenericPath/URL.py
pyTooling/GenericPath/__init__.py
pyTooling/Graph/GraphML.py
pyTooling/Graph/__init__.py
pyTooling/Licensing/__init__.py
pyTooling/LinkedList/__init__.py
pyTooling/MetaClasses/__init__.py
pyTooling/Packaging/__init__.py
pyTooling/Platform/__init__.py
pyTooling/StateMachine/__init__.py
pyTooling/Stopwatch/__init__.py
pyTooling/TerminalUI/__init__.py
pyTooling/Tracing/__init__.py
pyTooling/Tree/__init__.py
pyTooling/Versioning/__init__.py
pyTooling/Warning/__init__.py
pytooling-8.11.0.dist-info/licenses/LICENSE.md
pytooling-8.11.0.dist-info/METADATA
pytooling-8.11.0.dist-info/WHEEL
pytooling-8.11.0.dist-info/top_level.txt
pytooling-8.11.0.dist-info/RECORD
