Metadata-Version: 2.4
Name: pyTooling
Version: 8.11.0
Summary: pyTooling is a powerful collection of arbitrary useful classes, decorators, meta-classes and exceptions.
Home-page: https://GitHub.com/pyTooling/pyTooling
Author: Patrick Lehmann
Author-email: Paebbels@gmail.com
License: Apache-2.0
Project-URL: Documentation, https://pyTooling.GitHub.io/pyTooling
Project-URL: Source Code, https://GitHub.com/pyTooling/pyTooling
Project-URL: Issue Tracker, https://GitHub.com/pyTooling/pyTooling/issues
Keywords: abstract,argparse,attributes,bfs,cli,console,data structure,decorators,dfs,double linked list,exceptions,file system statistics,generators,generic library,generic path,geometry,graph,installation,iterators,licensing,linked list,message logging,meta-classes,overloading,override,packaging,path,platform,setuptools,shapes,shell,singleton,slots,terminal,text user interface,stopwatch,tree,TUI,url,versioning,volumes,warning,wheel
Classifier: Operating System :: OS Independent
Classifier: Intended Audience :: Developers
Classifier: Topic :: Utilities
Classifier: License :: OSI Approved :: Apache Software License
Classifier: Programming Language :: Python :: 3 :: Only
Classifier: Programming Language :: Python :: 3.11
Classifier: Programming Language :: Python :: 3.12
Classifier: Programming Language :: Python :: 3.13
Classifier: Programming Language :: Python :: 3.14
Classifier: Development Status :: 5 - Production/Stable
Requires-Python: >=3.11
License-File: LICENSE.md
Provides-Extra: doc
Requires-Dist: ruamel.yaml~=0.18.0; extra == "doc"
Requires-Dist: docutils_stubs~=0.0.22; extra == "doc"
Requires-Dist: colorama>=0.4.6; extra == "doc"
Requires-Dist: sphinx-copybutton>=0.5.0; extra == "doc"
Requires-Dist: setuptools>=80.0; extra == "doc"
Requires-Dist: sphinx_rtd_theme~=3.0; extra == "doc"
Requires-Dist: sphinx~=8.2; extra == "doc"
Requires-Dist: sphinxcontrib-mermaid~=1.0; extra == "doc"
Requires-Dist: sphinx_design~=0.6.0; extra == "doc"
Requires-Dist: sphinx_autodoc_typehints~=3.5; extra == "doc"
Requires-Dist: autoapi>=2.0.1; extra == "doc"
Requires-Dist: docutils~=0.21.0; extra == "doc"
Requires-Dist: sphinx_reports~=0.9.0; extra == "doc"
Provides-Extra: test
Requires-Dist: ruamel.yaml~=0.18.0; extra == "test"
Requires-Dist: types-setuptools>=80.9; extra == "test"
Requires-Dist: treelib~=1.7; extra == "test"
Requires-Dist: pytest-cov~=7.0; extra == "test"
Requires-Dist: requests>=2.32; extra == "test"
Requires-Dist: colorama~=0.4.6; extra == "test"
Requires-Dist: igraph~=0.11.0; extra == "test"
Requires-Dist: Coverage~=7.13; extra == "test"
Requires-Dist: lxml<7.0,>=5.4; extra == "test"
Requires-Dist: pytest~=9.0; extra == "test"
Requires-Dist: aiohttp>=3.12; extra == "test"
Requires-Dist: itertree~=1.1; extra == "test"
Requires-Dist: types-colorama>=0.4.15; extra == "test"
Requires-Dist: networkx~=3.4; extra == "test"
Requires-Dist: anytree~=2.13; extra == "test"
Requires-Dist: setuptools>=80.0; extra == "test"
Requires-Dist: doubly-py-linked-list~=1.1; extra == "test"
Requires-Dist: pytest-benchmark>=4.0.0; extra == "test"
Requires-Dist: typing_extensions~=4.15; extra == "test"
Requires-Dist: mypy[reports]~=1.19; extra == "test"
Provides-Extra: pypi
Requires-Dist: aiohttp>=3.12; extra == "pypi"
Requires-Dist: packaging>=25.0; extra == "pypi"
Requires-Dist: requests>=2.32; extra == "pypi"
Provides-Extra: packaging
Requires-Dist: setuptools>=80.0; extra == "packaging"
Provides-Extra: terminal
Requires-Dist: colorama~=0.4.6; extra == "terminal"
Provides-Extra: yaml
Requires-Dist: ruamel.yaml~=0.18; extra == "yaml"
Provides-Extra: all
Requires-Dist: ruamel.yaml~=0.18.0; extra == "all"
Requires-Dist: types-setuptools>=80.9; extra == "all"
Requires-Dist: treelib~=1.7; extra == "all"
Requires-Dist: pytest-cov~=7.0; extra == "all"
Requires-Dist: requests>=2.32; extra == "all"
Requires-Dist: ruamel.yaml~=0.18; extra == "all"
Requires-Dist: colorama~=0.4.6; extra == "all"
Requires-Dist: igraph~=0.11.0; extra == "all"
Requires-Dist: Coverage~=7.13; extra == "all"
Requires-Dist: lxml<7.0,>=5.4; extra == "all"
Requires-Dist: sphinx_reports~=0.9.0; extra == "all"
Requires-Dist: pytest~=9.0; extra == "all"
Requires-Dist: colorama>=0.4.6; extra == "all"
Requires-Dist: sphinx_rtd_theme~=3.0; extra == "all"
Requires-Dist: sphinxcontrib-mermaid~=1.0; extra == "all"
Requires-Dist: aiohttp>=3.12; extra == "all"
Requires-Dist: mypy[reports]~=1.19; extra == "all"
Requires-Dist: itertree~=1.1; extra == "all"
Requires-Dist: sphinx_autodoc_typehints~=3.5; extra == "all"
Requires-Dist: docutils~=0.21.0; extra == "all"
Requires-Dist: types-colorama>=0.4.15; extra == "all"
Requires-Dist: aiohttp>=3.12; extra == "all"
Requires-Dist: sphinx-copybutton>=0.5.0; extra == "all"
Requires-Dist: setuptools>=80.0; extra == "all"
Requires-Dist: networkx~=3.4; extra == "all"
Requires-Dist: anytree~=2.13; extra == "all"
Requires-Dist: doubly-py-linked-list~=1.1; extra == "all"
Requires-Dist: sphinx~=8.2; extra == "all"
Requires-Dist: pytest-benchmark>=4.0.0; extra == "all"
Requires-Dist: typing_extensions~=4.15; extra == "all"
Requires-Dist: sphinx_design~=0.6.0; extra == "all"
Requires-Dist: autoapi>=2.0.1; extra == "all"
Requires-Dist: packaging>=25.0; extra == "all"
Requires-Dist: docutils_stubs~=0.0.22; extra == "all"
Dynamic: author
Dynamic: author-email
Dynamic: classifier
Dynamic: description
Dynamic: description-content-type
Dynamic: home-page
Dynamic: keywords
Dynamic: license
Dynamic: license-file
Dynamic: project-url
Dynamic: provides-extra
Dynamic: requires-python
Dynamic: summary
